{
  "date": "2026-03-30",
  "signal": {
    "confirmed_allocation": 0.0,
    "allocation_label": "0% Equities / 100% SGOV",
    "raw_score": 0,
    "confirmed_score": 0,
    "sub_signals": {
      "ema200": {
        "value": false,
        "detail": "SPY 631.97 < EMA200 658.15"
      },
      "adx_di": {
        "value": false,
        "detail": "ADX 40.7 > 25, +DI 10.8 < -DI 42.9"
      },
      "roc126": {
        "value": false,
        "detail": "ROC126 -4.0% < 0"
      }
    },
    "days_at_confirmed": 5,
    "days_at_pending": 0,
    "pending_change": null
  },
  "portfolio": {
    "tickers": [
      "AAPL",
      "NVDA",
      "MSFT",
      "AMZN",
      "GOOG"
    ],
    "cash_etf": "SGOV",
    "target_alloc": {
      "equities": 0.0,
      "sgov": 1.0
    }
  },
  "dca": {
    "monthly_deposit": 3000,
    "per_stock": 0.0,
    "sgov": 3000.0
  },
  "watch": [
    {
      "icon": "below",
      "text": "SPY is 4.0% below EMA200 \u2014 needs to cross above for +1 point"
    },
    {
      "icon": "warning",
      "text": "ADX at 40.7 (above 25), but +DI < -DI"
    },
    {
      "icon": "below",
      "text": "6-month momentum is negative (-4.0%) \u2014 watch for turn positive"
    }
  ],
  "action_required": "NONE"
}